paramit/__init__.py
paramit/constants.py
paramit/cuda.py
paramit/nb.py
paramit/cli/__init__.py
paramit/cli/__main__.py
paramit-0.2.4.dist-info/METADATA
paramit-0.2.4.dist-info/WHEEL
paramit-0.2.4.dist-info/entry_points.txt
paramit-0.2.4.dist-info/licenses/LICENSE
paramit-0.2.4.dist-info/RECORD
