Metadata-Version: 2.3
Name: paramit
Version: 0.2.4
Summary: Parameterize Python scripts/notebooks all from the command line.
Author-email: Towaki Takikawa <tovacinni@gmail.com>, Allen Wang <allen.houze.wang@gmail.com>
License-File: LICENSE
Requires-Python: >=3.9
Requires-Dist: gitpython>=3.1.43
Requires-Dist: ipython>=8.18.0
Requires-Dist: jupytext>=1.16.3
Requires-Dist: libcst>=1.4.0
Requires-Dist: nbconvert>=7.16.4
Requires-Dist: nbformat>=5.10.4
Requires-Dist: platformdirs>=4.2.2
Requires-Dist: pydantic>=2.7.4
Requires-Dist: subprocess-tee>=0.4.2
Requires-Dist: tomli-w>=1.0.0
Requires-Dist: tomli>=2.0.1
Provides-Extra: notebook
Requires-Dist: notebook>=7.2.1; extra == 'notebook'
